meanCalculation
