Metadata-Version: 1.0
Name: meanCalculation
Version: 5.0
Summary: calculation of mean and Std deviation
Home-page: UNKNOWN
Author: UNKNOWN
Author-email: varshakt6@gmail.com
License: UNKNOWN
Platform: UNKNOWN
